lightning_pose/__init__.py
lightning_pose/api/__init__.py
lightning_pose/api/model.py
lightning_pose/api/model_config.py
lightning_pose/callbacks.py
lightning_pose/cli/__init__.py
lightning_pose/cli/commands/__init__.py
lightning_pose/cli/commands/crop.py
lightning_pose/cli/commands/predict.py
lightning_pose/cli/commands/remap.py
lightning_pose/cli/commands/run_app.py
lightning_pose/cli/commands/train.py
lightning_pose/cli/friendly.py
lightning_pose/cli/main.py
lightning_pose/cli/types.py
lightning_pose/data/__init__.py
lightning_pose/data/augmentations.py
lightning_pose/data/cameras.py
lightning_pose/data/dali.py
lightning_pose/data/datamodules.py
lightning_pose/data/datasets.py
lightning_pose/data/datatypes.py
lightning_pose/data/utils.py
lightning_pose/losses/__init__.py
lightning_pose/losses/factory.py
lightning_pose/losses/helpers.py
lightning_pose/losses/losses.py
lightning_pose/metrics.py
lightning_pose/migrations/__init__.py
lightning_pose/migrations/migrations.py
lightning_pose/migrations/rename_time_directories.py
lightning_pose/model.py
lightning_pose/models/__init__.py
lightning_pose/models/backbones/__init__.py
lightning_pose/models/backbones/torchvision.py
lightning_pose/models/backbones/vit_sam.py
lightning_pose/models/backbones/vits.py
lightning_pose/models/base.py
lightning_pose/models/heads/__init__.py
lightning_pose/models/heads/heatmap.py
lightning_pose/models/heads/heatmap_mhcrnn.py
lightning_pose/models/heads/regression.py
lightning_pose/models/heatmap_tracker.py
lightning_pose/models/heatmap_tracker_mhcrnn.py
lightning_pose/models/heatmap_tracker_multiview.py
lightning_pose/models/regression_tracker.py
lightning_pose/train.py
lightning_pose/utils/__init__.py
lightning_pose/utils/cropzoom.py
lightning_pose/utils/io.py
lightning_pose/utils/pca.py
lightning_pose/utils/predictions.py
lightning_pose/utils/scripts.py
lightning_pose-2.0.4.dist-info/METADATA
lightning_pose-2.0.4.dist-info/WHEEL
lightning_pose-2.0.4.dist-info/entry_points.txt
lightning_pose-2.0.4.dist-info/licenses/LICENSE
lightning_pose-2.0.4.dist-info/RECORD
