Metadata-Version: 2.4
Name: lightning-pose
Version: 2.0.4
Summary: Semi-supervised pose estimation using pytorch lightning
License-Expression: MIT
License-File: LICENSE
Keywords: machine learning,deep learning,computer_vision
Author: Dan Biderman
Author-email: danbider@gmail.com
Maintainer: Karan Sikka
Maintainer-email: karanssikka@gmail.com
Requires-Python: >=3.10
Classifier: Development Status :: 5 - Production/Stable
Classifier: Intended Audience :: Science/Research
Classifier: License :: OSI Approved :: MIT License
Classifier: Programming Language :: Python :: 3
Classifier: Programming Language :: Python :: 3.10
Classifier: Programming Language :: Python :: 3.11
Classifier: Programming Language :: Python :: 3.12
Classifier: Topic :: Scientific/Engineering :: Artificial Intelligence
Classifier: Topic :: Scientific/Engineering :: Image Processing
Classifier: Topic :: Scientific/Engineering :: Visualization
Provides-Extra: dev
Provides-Extra: extra-models
Requires-Dist: Sphinx ; extra == "dev"
Requires-Dist: aniposelib
Requires-Dist: autopep8 ; extra == "dev"
Requires-Dist: flake8 ; extra == "dev"
Requires-Dist: h5py
Requires-Dist: hydra-core
Requires-Dist: imaug
Requires-Dist: isort ; extra == "dev"
Requires-Dist: kornia
Requires-Dist: lightning (>=2.5.0,<2.6.0)
Requires-Dist: lightning-bolts ; extra == "extra-models"
Requires-Dist: matplotlib
Requires-Dist: moviepy (>=2.0.0)
Requires-Dist: numpy (>=2.0.0)
Requires-Dist: nvidia-dali-cuda110
Requires-Dist: opencv-python-headless
Requires-Dist: pandas (>=2.0.0)
Requires-Dist: pillow
Requires-Dist: pytest ; extra == "dev"
Requires-Dist: pytest-html ; extra == "dev"
Requires-Dist: pytest-mock ; extra == "dev"
Requires-Dist: pytorch-lightning (>=2.5.0,<2.6.0)
Requires-Dist: safetensors
Requires-Dist: scikit-learn (>=1.5.0)
Requires-Dist: sphinx-argparse ; extra == "dev"
Requires-Dist: sphinx-automodapi ; extra == "dev"
Requires-Dist: sphinx-copybutton ; extra == "dev"
Requires-Dist: sphinx-design ; extra == "dev"
Requires-Dist: sphinx-rtd-dark-mode ; extra == "dev"
Requires-Dist: sphinx_rtd_theme ; extra == "dev"
Requires-Dist: tbparse (<1.0.0) ; extra == "dev"
Requires-Dist: tensorboard (<3.0.0)
Requires-Dist: torch (<3.0.0)
Requires-Dist: torchtyping
Requires-Dist: torchvision (<0.25.0)
Requires-Dist: transformers (==4.52.4)
Requires-Dist: typeguard
Project-URL: Documentation, https://lightning-pose.readthedocs.io/
Project-URL: Repository, https://github.com/paninski-lab/lightning-pose
